[
  {
    "id": "p1",
    "name": "Apple",
    "description": "Crisp organic apples, perfect for snacking.",
    "category": "fruits",
    "price": 2.49,
    "unit": "kg",
    "stock": 120,
    "featured": true,
    "rating": 4.6,
    "reviews": 54,
    "image": "assets/images/apple.jpg"
  },
  {
    "id": "p2",
    "name": "Banana",
    "description": "Sweet organic bananas, rich in potassium.",
    "category": "fruits",
    "price": 1.29,
    "unit": "kg",
    "stock": 200,
    "featured": true,
    "rating": 4.5,
    "reviews": 68,
    "image": "assets/images/banana.jpg"
  },
  {
    "id": "p3",
    "name": "Kiwi",
    "description": "Tangy green kiwi, full of vitamin C.",
    "category": "fruits",
    "price": 3.99,
    "unit": "kg",
    "stock": 60,
    "featured": false,
    "rating": 4.4,
    "reviews": 21,
    "image": "assets/images/kiwi.jpg"
  },
  {
    "id": "p4",
    "name": "Strawberry",
    "description": "Fresh organic strawberries, sweet and juicy.",
    "category": "fruits",
    "price": 4.99,
    "unit": "box",
    "stock": 80,
    "featured": true,
    "rating": 4.8,
    "reviews": 112,
    "image": "assets/images/strawberry.jpg"
  },
  {
    "id": "p5",
    "name": "Grapes",
    "description": "Seedless grapes, great for snacking and desserts.",
    "category": "fruits",
    "price": 3.49,
    "unit": "kg",
    "stock": 90,
    "featured": false,
    "rating": 4.3,
    "reviews": 34,
    "image": "assets/images/grapes.jpg"
  },
  {
    "id": "p6",
    "name": "Orange",
    "description": "Juicy oranges, ideal for fresh-squeezed juice.",
    "category": "fruits",
    "price": 2.99,
    "unit": "kg",
    "stock": 150,
    "featured": false,
    "rating": 4.2,
    "reviews": 47,
    "image": "assets/images/orange.jpg"
  },
  {
    "id": "p7",
    "name": "Pomegranate",
    "description": "Rich and tangy pomegranates (annar).",
    "category": "fruits",
    "price": 5.49,
    "unit": "kg",
    "stock": 40,
    "featured": true,
    "rating": 4.7,
    "reviews": 29,
    "image": "assets/images/pomegranate.jpg"
  },
  {
    "id": "p8",
    "name": "Coconut Water",
    "description": "Refreshing natural coconut water, chilled.",
    "category": "beverages",
    "price": 2.99,
    "unit": "bottle",
    "stock": 100,
    "featured": true,
    "rating": 4.5,
    "reviews": 73,
    "image": "assets/images/coconut-water.jpg"
  },
  {
    "id": "p9",
    "name": "Pineapple",
    "description": "Tropical pineapples, sweet and fragrant.",
    "category": "fruits",
    "price": 3.79,
    "unit": "each",
    "stock": 55,
    "featured": false,
    "rating": 4.4,
    "reviews": 38,
    "image": "assets/images/pineapple.jpg"
  },
  {
    "id": "p10",
    "name": "Chikoo",
    "description": "Also known as sapota, sweet and grainy texture.",
    "category": "fruits",
    "price": 3.29,
    "unit": "kg",
    "stock": 70,
    "featured": false,
    "rating": 4.1,
    "reviews": 18,
    "image": "assets/images/chikoo.jpg"
  },
  {
    "id": "p11",
    "name": "Guava",
    "description": "Aromatic guavas, excellent for jams and juice.",
    "category": "fruits",
    "price": 2.79,
    "unit": "kg",
    "stock": 85,
    "featured": false,
    "rating": 4.0,
    "reviews": 22,
    "image": "assets/images/guava.jpg"
  },
  {
    "id": "p12",
    "name": "Papaya",
    "description": "Ripe papayas, soft and sweet.",
    "category": "fruits",
    "price": 2.59,
    "unit": "kg",
    "stock": 95,
    "featured": false,
    "rating": 4.2,
    "reviews": 27,
    "image": "assets/images/papaya.jpg"
  },
  {
    "id": "p13",
    "name": "Mango",
    "description": "Seasonal alphonso-style mangoes, ultra sweet.",
    "category": "fruits",
    "price": 6.99,
    "unit": "kg",
    "stock": 35,
    "featured": true,
    "rating": 4.9,
    "reviews": 210,
    "image": "assets/images/mango.jpg"
  },
  {
    "id": "p14",
    "name": "Muskmelon",
    "description": "Sweet and aromatic muskmelon, fresh from the farm.",
    "category": "fruits",
    "price": 3.49,
    "unit": "each",
    "stock": 45,
    "featured": true,
    "rating": 4.3,
    "reviews": 12,
    "image": "assets/images/muskmelon.jpg"
  },
  {
    "id": "p15",
    "name": "Watermelon",
    "description": "Juicy and refreshing red watermelon.",
    "category": "fruits",
    "price": 4.99,
    "unit": "each",
    "stock": 30,
    "featured": true,
    "rating": 4.7,
    "reviews": 89,
    "image": "assets/images/watermelon.jpg"
  }
]